CHANGES.txt
CMakeLists.txt
LICENSE
MANIFEST.in
README.md
requirements.txt
setup.py
pyscannerbit/__init__.py
pyscannerbit/defaults.py
pyscannerbit/ext_module.py
pyscannerbit/hdf5_help.py
pyscannerbit/plotting.py
pyscannerbit/plottools.py
pyscannerbit/processify.py
pyscannerbit/scan.py
pyscannerbit/utils.py
pyscannerbit.egg-info/PKG-INFO
pyscannerbit.egg-info/SOURCES.txt
pyscannerbit.egg-info/dependency_links.txt
pyscannerbit.egg-info/not-zip-safe
pyscannerbit.egg-info/requires.txt
pyscannerbit.egg-info/top_level.txt
pyscannerbit/__pycache__/__init__.cpython-310.pyc
pyscannerbit/__pycache__/defaults.cpython-310.pyc
pyscannerbit/__pycache__/ext_module.cpython-310.pyc
pyscannerbit/__pycache__/hdf5_help.cpython-310.pyc
pyscannerbit/__pycache__/plottools.cpython-310.pyc
pyscannerbit/__pycache__/processify.cpython-310.pyc
pyscannerbit/__pycache__/scan.cpython-310.pyc
pyscannerbit/__pycache__/utils.cpython-310.pyc
pyscannerbit/scannerbit/ScannerBit_stripped.tar
pyscannerbit/scannerbit/untar/ScannerBit/nullfile
tests/basic_test.py
tests/default.py
tests/example.py
tests/import_yaml.py
tests/interface_test.py
tests/sb.py
tests/scan_object_test.py
tests/test.py
tests/test.yaml
tests/test_all_scanners.png
tests/test_all_scanners.py
tests/test_all_scanners_ext.py
tests/test_ext.py
tests/test_import.py
tests/tests.py
tests/__pycache__/default.cpython-310.pyc
tests/__pycache__/import_yaml.cpython-310.pyc
tests/__pycache__/sb.cpython-310.pyc
tests/pyscannerbit_run_data/pyScannerBit.yaml
tests/pyscannerbit_run_data/logs/default.log
tests/pyscannerbit_run_data/multinest_scan/pyScannerBit.yaml
tests/pyscannerbit_run_data/multinest_scan/logs/default.log
tests/pyscannerbit_run_data/multinest_scan/logs/default.log_0
tests/pyscannerbit_run_data/multinest_scan/logs/default.log_1
tests/pyscannerbit_run_data/multinest_scan/samples/results.hdf5
tests/pyscannerbit_run_data/multinest_scan/scanner_plugins/ALT_MIN_LOGL_IN_USE
tests/pyscannerbit_run_data/multinest_scan/scanner_plugins/MultiNest/native-.txt
tests/pyscannerbit_run_data/multinest_scan/scanner_plugins/MultiNest/native-IS.iterinfo
tests/pyscannerbit_run_data/multinest_scan/scanner_plugins/MultiNest/native-IS.points
